odoo/addons/survey_certification_sending/README.rst
odoo/addons/survey_certification_sending/__init__.py
odoo/addons/survey_certification_sending/__manifest__.py
odoo/addons/survey_certification_sending/i18n/es.po
odoo/addons/survey_certification_sending/i18n/it.po
odoo/addons/survey_certification_sending/i18n/survey_certification_sending.pot
odoo/addons/survey_certification_sending/models/__init__.py
odoo/addons/survey_certification_sending/models/mail_template.py
odoo/addons/survey_certification_sending/models/res_partner.py
odoo/addons/survey_certification_sending/models/survey_survey.py
odoo/addons/survey_certification_sending/models/survey_user_input.py
odoo/addons/survey_certification_sending/readme/CONTRIBUTORS.md
odoo/addons/survey_certification_sending/readme/DESCRIPTION.md
odoo/addons/survey_certification_sending/readme/USAGE.md
odoo/addons/survey_certification_sending/static/description/icon.png
odoo/addons/survey_certification_sending/static/description/index.html
odoo/addons/survey_certification_sending/tests/__init__.py
odoo/addons/survey_certification_sending/tests/test_survey_certification_sending.py
odoo/addons/survey_certification_sending/views/res_partner_views.xml
odoo/addons/survey_certification_sending/views/survey_survey_views.xml
odoo/addons/survey_certification_sending/views/survey_templates.xml
odoo/addons/survey_certification_sending/views/survey_user_views.xml
odoo_addon_survey_certification_sending-17.0.1.1.0.2.dist-info/METADATA
odoo_addon_survey_certification_sending-17.0.1.1.0.2.dist-info/WHEEL
odoo_addon_survey_certification_sending-17.0.1.1.0.2.dist-info/top_level.txt
odoo_addon_survey_certification_sending-17.0.1.1.0.2.dist-info/RECORD
